{"name":"Aspach","code":"aspach","wappen":"https://upload.wikimedia.org/wikipedia/commons/thumb/3/3e/AUT_Aspach_COA.png/200px-AUT_Aspach_COA.png","bilder":[{"thumb":"https://upload.wikimedia.org/wikipedia/commons/thumb/a/aa/Aspach_Pfarrhof1.jpg/400px-Aspach_Pfarrhof1.jpg","url":"https://upload.wikimedia.org/wikipedia/commons/a/aa/Aspach_Pfarrhof1.jpg","attribution":"<a href=\"//commons.wikimedia.org/wiki/User:BSonne\" title=\"User:BSonne\">BSonne</a>, CC BY-SA 3.0 <https://creativecommons.org/licenses/by-sa/3.0>, via Wikimedia Commons"},{"thumb":"https://upload.wikimedia.org/wikipedia/commons/thumb/3/36/Aspach_Stiblersaal1.jpg/400px-Aspach_Stiblersaal1.jpg","url":"https://upload.wikimedia.org/wikipedia/commons/3/36/Aspach_Stiblersaal1.jpg","attribution":"<a href=\"//commons.wikimedia.org/wiki/User:BSonne\" title=\"User:BSonne\">BSonne</a>, CC BY-SA 3.0 <https://creativecommons.org/licenses/by-sa/3.0>, via Wikimedia Commons"},{"thumb":"https://upload.wikimedia.org/wikipedia/commons/thumb/6/61/Aspach_Stiblersaal2.jpg/400px-Aspach_Stiblersaal2.jpg","url":"https://upload.wikimedia.org/wikipedia/commons/6/61/Aspach_Stiblersaal2.jpg","attribution":"<a href=\"//commons.wikimedia.org/wiki/User:BSonne\" title=\"User:BSonne\">BSonne</a>, CC BY-SA 3.0 <https://creativecommons.org/licenses/by-sa/3.0>, via Wikimedia Commons"},{"thumb":"https://upload.wikimedia.org/wikipedia/commons/thumb/7/74/Aspach_Gemeindeamt1.jpg/400px-Aspach_Gemeindeamt1.jpg","url":"https://upload.wikimedia.org/wikipedia/commons/7/74/Aspach_Gemeindeamt1.jpg","attribution":"<a href=\"//commons.wikimedia.org/wiki/User:BSonne\" title=\"User:BSonne\">BSonne</a>, CC BY-SA 3.0 <https://creativecommons.org/licenses/by-sa/3.0>, via Wikimedia Commons"},{"thumb":"https://upload.wikimedia.org/wikipedia/commons/thumb/e/e9/Aspach_Gemeindeamt2.jpg/400px-Aspach_Gemeindeamt2.jpg","url":"https://upload.wikimedia.org/wikipedia/commons/e/e9/Aspach_Gemeindeamt2.jpg","attribution":"<a href=\"//commons.wikimedia.org/wiki/User:BSonne\" title=\"User:BSonne\">BSonne</a>, CC BY-SA 3.0 <https://creativecommons.org/licenses/by-sa/3.0>, via Wikimedia Commons"}],"plz":"5252","kennziffer":"40402","burgermeister":"Georg Gattringer","flaeche":31.46,"homepage":"aspach.at/","bezirk":"Braunau","bundesland":"Oberösterreich","email":"unknown","tel":"0775 57355","tel_int":"International : +43 7755 7355","adress":"Marktplatz 9 5252 Aspach","location":{"longitude":13.3046189,"latitude":48.18499425},"population":2596}