{"name":"Kopfing im Innkreis","code":"kopfing-im-innkreis","wappen":"https://upload.wikimedia.org/wikipedia/commons/thumb/e/e5/Coat_of_arms_Kopfing.svg/200px-Coat_of_arms_Kopfing.svg.png","bilder":[{"thumb":"https://upload.wikimedia.org/wikipedia/commons/thumb/8/81/Pfarrhof_-_Kopfing.jpg/400px-Pfarrhof_-_Kopfing.jpg","url":"https://upload.wikimedia.org/wikipedia/commons/8/81/Pfarrhof_-_Kopfing.jpg","attribution":"<a href=\"//commons.wikimedia.org/wiki/User:PLauppert\" title=\"User:PLauppert\">Peter Lauppert</a>, CC BY-SA 4.0 <https://creativecommons.org/licenses/by-sa/4.0>, via Wikimedia Commons"},{"thumb":"https://upload.wikimedia.org/wikipedia/commons/thumb/c/c0/Pfarrkirche_-_Kopfing.jpg/400px-Pfarrkirche_-_Kopfing.jpg","url":"https://upload.wikimedia.org/wikipedia/commons/c/c0/Pfarrkirche_-_Kopfing.jpg","attribution":"<a href=\"//commons.wikimedia.org/wiki/User:PLauppert\" title=\"User:PLauppert\">Peter Lauppert</a>, CC BY-SA 4.0 <https://creativecommons.org/licenses/by-sa/4.0>, via Wikimedia Commons"},{"thumb":"https://upload.wikimedia.org/wikipedia/commons/thumb/a/af/Friedhof_Aufbahrungshalle_-_Kopfing.jpg/400px-Friedhof_Aufbahrungshalle_-_Kopfing.jpg","url":"https://upload.wikimedia.org/wikipedia/commons/a/af/Friedhof_Aufbahrungshalle_-_Kopfing.jpg","attribution":"<a href=\"//commons.wikimedia.org/wiki/User:PLauppert\" title=\"User:PLauppert\">Peter Lauppert</a>, CC BY-SA 4.0 <https://creativecommons.org/licenses/by-sa/4.0>, via Wikimedia Commons"},{"thumb":"https://upload.wikimedia.org/wikipedia/commons/thumb/2/23/Kriegerdenkmal_W_-_Kopfing.jpg/400px-Kriegerdenkmal_W_-_Kopfing.jpg","url":"https://upload.wikimedia.org/wikipedia/commons/2/23/Kriegerdenkmal_W_-_Kopfing.jpg","attribution":"<a href=\"//commons.wikimedia.org/wiki/User:PLauppert\" title=\"User:PLauppert\">Peter Lauppert</a>, CC BY-SA 4.0 <https://creativecommons.org/licenses/by-sa/4.0>, via Wikimedia Commons"}],"plz":"4794","kennziffer":"41411","burgermeister":"Bernhard Schasching","flaeche":33.3,"homepage":"kopfing.at/","bezirk":"Schärding","bundesland":"Oberösterreich","email":"unknown","tel":"0776 32205","tel_int":"International : +43 7763 2205","adress":"Hauptstraße 95 4794 Kopfing im Innkreis","location":{"longitude":13.6593294,"latitude":48.4385443},"population":2008}