{"name":"Sankt Thomas","code":"sankt-thomas","wappen":"https://upload.wikimedia.org/wikipedia/commons/thumb/c/c7/Wappen_at_st_thomas.png/200px-Wappen_at_st_thomas.png","bilder":[{"thumb":"https://upload.wikimedia.org/wikipedia/commons/thumb/1/11/St._Thomas%2C_Pfarrkirche.jpg/400px-St._Thomas%2C_Pfarrkirche.jpg","url":"https://upload.wikimedia.org/wikipedia/commons/1/11/St._Thomas%2C_Pfarrkirche.jpg","attribution":"<a href=\"//commons.wikimedia.org/w/index.php?title=User:FranzOvilava&amp;action=edit&amp;redlink=1\" class=\"new\" title=\"User:FranzOvilava (page does not exist)\">FranzOvilava</a>, CC BY-SA 3.0 at <https://creativecommons.org/licenses/by-sa/3.0/at/deed.en>, via Wikimedia Commons"}],"plz":"4732","kennziffer":"40826","burgermeister":"Raimund Floimayr","flaeche":6.07,"homepage":"sankt-thomas.at/","bezirk":"Grieskirchen","bundesland":"Oberösterreich","email":"unknown","tel":"0727 77212","tel_int":"International : +43 7277 7212","adress":"St. Thomas 100 4732 St. Thomas","location":{"longitude":13.8840248,"latitude":48.2852507},"population":545}