{"name":"Schlins","code":"schlins","wappen":"https:undefined","bilder":[{"thumb":"https://upload.wikimedia.org/wikipedia/commons/thumb/a/a0/BurgruineJagdberg4.JPG/400px-BurgruineJagdberg4.JPG","url":"https://upload.wikimedia.org/wikipedia/commons/a/a0/BurgruineJagdberg4.JPG","attribution":"<a href=\"//commons.wikimedia.org/wiki/User:B%C3%B6hringer\" title=\"User:Böhringer\">böhringer friedrich</a>, CC BY-SA 2.5 <https://creativecommons.org/licenses/by-sa/2.5>, via Wikimedia Commons"},{"thumb":"https://upload.wikimedia.org/wikipedia/commons/thumb/9/9d/BurgruineJagdberg5.JPG/400px-BurgruineJagdberg5.JPG","url":"https://upload.wikimedia.org/wikipedia/commons/9/9d/BurgruineJagdberg5.JPG","attribution":"<a href=\"//commons.wikimedia.org/wiki/User:B%C3%B6hringer\" title=\"User:Böhringer\">böhringer friedrich</a>, CC BY-SA 2.5 <https://creativecommons.org/licenses/by-sa/2.5>, via Wikimedia Commons"},{"thumb":"https://upload.wikimedia.org/wikipedia/commons/thumb/f/fa/Wohngeb%C3%A4ude_am_Jagdberg.jpg/400px-Wohngeb%C3%A4ude_am_Jagdberg.jpg","url":"https://upload.wikimedia.org/wikipedia/commons/f/fa/Wohngeb%C3%A4ude_am_Jagdberg.jpg","attribution":"<a href=\"//commons.wikimedia.org/wiki/User:B%C3%B6hringer\" title=\"User:Böhringer\">böhringer friedrich</a>, CC BY-SA 2.5 <https://creativecommons.org/licenses/by-sa/2.5>, via Wikimedia Commons"},{"thumb":"https://upload.wikimedia.org/wikipedia/commons/thumb/e/ea/Am_Jagdberg_Schlins.jpg/400px-Am_Jagdberg_Schlins.jpg","url":"https://upload.wikimedia.org/wikipedia/commons/e/ea/Am_Jagdberg_Schlins.jpg","attribution":"<a href=\"//commons.wikimedia.org/wiki/User:B%C3%B6hringer\" title=\"User:Böhringer\">böhringer friedrich</a>, CC BY-SA 2.5 <https://creativecommons.org/licenses/by-sa/2.5>, via Wikimedia Commons"},{"thumb":"https://upload.wikimedia.org/wikipedia/commons/thumb/c/c7/Schule_am_Jagdberg.jpg/399px-Schule_am_Jagdberg.jpg","url":"https://upload.wikimedia.org/wikipedia/commons/c/c7/Schule_am_Jagdberg.jpg","attribution":"<a href=\"//commons.wikimedia.org/wiki/User:B%C3%B6hringer\" title=\"User:Böhringer\">böhringer friedrich</a>, CC BY-SA 2.5 <https://creativecommons.org/licenses/by-sa/2.5>, via Wikimedia Commons"}],"plz":"6824","kennziffer":"80418","burgermeister":"Wolfgang Lässer","flaeche":6.03,"homepage":"schlins.at/","bezirk":"Feldkirch","bundesland":"Vorarlberg","email":"unknown","tel":"0552 483170","tel_int":"International : +43 5524 83170","adress":"Hauptstraße 47 6824 Schlins","location":{"longitude":9.698799774898374,"latitude":47.2058421},"population":2404}