{"name":"Brand-Nagelberg","code":"brand-nagelberg","wappen":"https://upload.wikimedia.org/wikipedia/commons/thumb/a/a0/AUT_Brand-Nagelberg_COA.jpg/200px-AUT_Brand-Nagelberg_COA.jpg","bilder":[{"thumb":"https://upload.wikimedia.org/wikipedia/commons/thumb/4/4b/Pfarrkirche_in_Alt-Nagelberg_S%C3%BCdseite_2015-08.jpg/400px-Pfarrkirche_in_Alt-Nagelberg_S%C3%BCdseite_2015-08.jpg","url":"https://upload.wikimedia.org/wikipedia/commons/4/4b/Pfarrkirche_in_Alt-Nagelberg_S%C3%BCdseite_2015-08.jpg","attribution":"<a href=\"//commons.wikimedia.org/wiki/User:Duke_of_W4\" title=\"User:Duke of W4\">Duke of W4</a>, CC BY-SA 4.0 <https://creativecommons.org/licenses/by-sa/4.0>, via Wikimedia Commons"},{"thumb":"https://upload.wikimedia.org/wikipedia/commons/thumb/c/ce/Cyperus_fuscus_sl25.jpg/400px-Cyperus_fuscus_sl25.jpg","url":"https://upload.wikimedia.org/wikipedia/commons/c/ce/Cyperus_fuscus_sl25.jpg","attribution":"<a href=\"//commons.wikimedia.org/wiki/User:Stefan.lefnaer\" title=\"User:Stefan.lefnaer\">Stefan.lefnaer</a>, CC BY-SA 4.0 <https://creativecommons.org/licenses/by-sa/4.0>, via Wikimedia Commons"},{"thumb":"https://upload.wikimedia.org/wikipedia/commons/thumb/4/45/Cyperus_fuscus_sl27.jpg/400px-Cyperus_fuscus_sl27.jpg","url":"https://upload.wikimedia.org/wikipedia/commons/4/45/Cyperus_fuscus_sl27.jpg","attribution":"<a href=\"//commons.wikimedia.org/wiki/User:Stefan.lefnaer\" title=\"User:Stefan.lefnaer\">Stefan.lefnaer</a>, CC BY-SA 4.0 <https://creativecommons.org/licenses/by-sa/4.0>, via Wikimedia Commons"},{"thumb":"https://upload.wikimedia.org/wikipedia/commons/thumb/5/5a/Cyperus_fuscus_sl26.jpg/400px-Cyperus_fuscus_sl26.jpg","url":"https://upload.wikimedia.org/wikipedia/commons/5/5a/Cyperus_fuscus_sl26.jpg","attribution":"<a href=\"//commons.wikimedia.org/wiki/User:Stefan.lefnaer\" title=\"User:Stefan.lefnaer\">Stefan.lefnaer</a>, CC BY-SA 4.0 <https://creativecommons.org/licenses/by-sa/4.0>, via Wikimedia Commons"},{"thumb":"https://upload.wikimedia.org/wikipedia/commons/thumb/1/10/Callitriche_palustris_s._str._sl35.jpg/400px-Callitriche_palustris_s._str._sl35.jpg","url":"https://upload.wikimedia.org/wikipedia/commons/1/10/Callitriche_palustris_s._str._sl35.jpg","attribution":"<a href=\"//commons.wikimedia.org/wiki/User:Stefan.lefnaer\" title=\"User:Stefan.lefnaer\">Stefan.lefnaer</a>, CC BY-SA 4.0 <https://creativecommons.org/licenses/by-sa/4.0>, via Wikimedia Commons"}],"plz":"3871, 3873","kennziffer":"30903","burgermeister":"Georg Einzinger","flaeche":36.7,"homepage":"brand-nagelberg.at/","bezirk":"Gmünd","bundesland":"Niederösterreich","email":"unknown","tel":"0285 97217","tel_int":"International : +43 2859 7217","adress":"Hauptstraße 117  3871 Alt-Nagelberg","location":{"longitude":14.9939789,"latitude":48.839173},"population":1546}