{"name":"Grinzens","code":"grinzens","wappen":"https://upload.wikimedia.org/wikipedia/commons/7/79/Wappen_at_grinzens.png","bilder":[{"thumb":"https://upload.wikimedia.org/wikipedia/commons/thumb/9/99/Kath._Pfarrkirche_hl._Antonius.JPG/400px-Kath._Pfarrkirche_hl._Antonius.JPG","url":"https://upload.wikimedia.org/wikipedia/commons/9/99/Kath._Pfarrkirche_hl._Antonius.JPG","attribution":"<a href=\"//commons.wikimedia.org/wiki/User:Alletto\" title=\"User:Alletto\">Alletto</a>, CC BY-SA 3.0 at <https://creativecommons.org/licenses/by-sa/3.0/at/deed.en>, via Wikimedia Commons"},{"thumb":"https://upload.wikimedia.org/wikipedia/commons/thumb/a/a5/Feuchtbiotop_Wirtsee_01.JPG/399px-Feuchtbiotop_Wirtsee_01.JPG","url":"https://upload.wikimedia.org/wikipedia/commons/a/a5/Feuchtbiotop_Wirtsee_01.JPG","attribution":"Simon Legner (<a href=\"https://de.wikipedia.org/wiki/Benutzer:Simon04\" class=\"extiw\" title=\"de:Benutzer:Simon04\">User:simon04</a>), CC BY-SA 4.0 <https://creativecommons.org/licenses/by-sa/4.0>, via Wikimedia Commons"},{"thumb":"https://upload.wikimedia.org/wikipedia/commons/thumb/b/b5/Feuchtbiotop_Wirtsee_02.JPG/400px-Feuchtbiotop_Wirtsee_02.JPG","url":"https://upload.wikimedia.org/wikipedia/commons/b/b5/Feuchtbiotop_Wirtsee_02.JPG","attribution":"Simon Legner (<a href=\"https://de.wikipedia.org/wiki/Benutzer:Simon04\" class=\"extiw\" title=\"de:Benutzer:Simon04\">User:simon04</a>), CC BY-SA 4.0 <https://creativecommons.org/licenses/by-sa/4.0>, via Wikimedia Commons"},{"thumb":"https://upload.wikimedia.org/wikipedia/commons/thumb/e/e5/Grinzens_%28IMG_3307%29.jpg/399px-Grinzens_%28IMG_3307%29.jpg","url":"https://upload.wikimedia.org/wikipedia/commons/e/e5/Grinzens_%28IMG_3307%29.jpg","attribution":"Simon Legner (<a href=\"https://de.wikipedia.org/wiki/Benutzer:Simon04\" class=\"extiw\" title=\"de:Benutzer:Simon04\">User:simon04</a>), CC BY-SA 4.0 <https://creativecommons.org/licenses/by-sa/4.0>, via Wikimedia Commons"},{"thumb":"https://upload.wikimedia.org/wikipedia/commons/thumb/4/4a/Grinzens_%28IMG_3310%29.jpg/399px-Grinzens_%28IMG_3310%29.jpg","url":"https://upload.wikimedia.org/wikipedia/commons/4/4a/Grinzens_%28IMG_3310%29.jpg","attribution":"Simon Legner (<a href=\"https://de.wikipedia.org/wiki/Benutzer:Simon04\" class=\"extiw\" title=\"de:Benutzer:Simon04\">User:simon04</a>), CC BY-SA 4.0 <https://creativecommons.org/licenses/by-sa/4.0>, via Wikimedia Commons"}],"plz":"6095","kennziffer":"70315","burgermeister":"Anton Bucher","flaeche":28.69,"homepage":"grinzens.tirol.gv.at/","bezirk":"Innsbruck-Land","bundesland":"Tirol","email":"unknown","tel":"0523 468387","tel_int":"International : +43 5234 68387","adress":"Kirchgasse 7 6095 Grinzens","location":{"longitude":11.2553871,"latitude":47.2306657},"population":1399}