{"name":"Göfis","code":"göfis","wappen":"https:undefined","bilder":[{"thumb":"https://upload.wikimedia.org/wikipedia/commons/thumb/0/07/HlSebastianG%C3%B6fis.jpg/400px-HlSebastianG%C3%B6fis.jpg","url":"https://upload.wikimedia.org/wikipedia/commons/0/07/HlSebastianG%C3%B6fis.jpg","attribution":"<a href=\"//commons.wikimedia.org/wiki/User:B%C3%B6hringer\" title=\"User:Böhringer\">böhringer friedrich</a>, CC BY-SA 2.5 <https://creativecommons.org/licenses/by-sa/2.5>, via Wikimedia Commons"},{"thumb":"https://upload.wikimedia.org/wikipedia/commons/thumb/e/e3/AGemeindeamtG%C3%B6fis.jpg/400px-AGemeindeamtG%C3%B6fis.jpg","url":"https://upload.wikimedia.org/wikipedia/commons/e/e3/AGemeindeamtG%C3%B6fis.jpg","attribution":"<a href=\"//commons.wikimedia.org/wiki/User:B%C3%B6hringer\" title=\"User:Böhringer\">böhringer friedrich</a>, CC BY-SA 2.5 <https://creativecommons.org/licenses/by-sa/2.5>, via Wikimedia Commons"},{"thumb":"https://upload.wikimedia.org/wikipedia/commons/thumb/8/81/GemeindeamtG%C3%B6fis.jpg/400px-GemeindeamtG%C3%B6fis.jpg","url":"https://upload.wikimedia.org/wikipedia/commons/8/81/GemeindeamtG%C3%B6fis.jpg","attribution":"<a href=\"//commons.wikimedia.org/wiki/User:B%C3%B6hringer\" title=\"User:Böhringer\">böhringer friedrich</a>, CC BY-SA 2.5 <https://creativecommons.org/licenses/by-sa/2.5>, via Wikimedia Commons"},{"thumb":"https://upload.wikimedia.org/wikipedia/commons/thumb/b/b0/Kirchstra%C3%9Fe_2%2C_G%C3%B6fis.JPG/400px-Kirchstra%C3%9Fe_2%2C_G%C3%B6fis.JPG","url":"https://upload.wikimedia.org/wikipedia/commons/b/b0/Kirchstra%C3%9Fe_2%2C_G%C3%B6fis.JPG","attribution":"<a href=\"//commons.wikimedia.org/wiki/User:B%C3%B6hringer\" title=\"User:Böhringer\">böhringer friedrich</a>, CC BY-SA 2.5 <https://creativecommons.org/licenses/by-sa/2.5>, via Wikimedia Commons"},{"thumb":"https://upload.wikimedia.org/wikipedia/commons/thumb/7/7b/Hl_Sebastian%2C_G%C3%B6fis.JPG/400px-Hl_Sebastian%2C_G%C3%B6fis.JPG","url":"https://upload.wikimedia.org/wikipedia/commons/7/7b/Hl_Sebastian%2C_G%C3%B6fis.JPG","attribution":"<a href=\"//commons.wikimedia.org/wiki/User:B%C3%B6hringer\" title=\"User:Böhringer\">böhringer friedrich</a>, CC BY-SA 2.5 <https://creativecommons.org/licenses/by-sa/2.5>, via Wikimedia Commons"}],"plz":"6811","kennziffer":"80407","burgermeister":"Thomas Lampert","flaeche":9.05,"homepage":"goefis.at/","bezirk":"Feldkirch","bundesland":"Vorarlberg","email":"unknown","tel":"0552 272715","tel_int":"International : +43 5522 72715","adress":"Kirchstraße 2 6811 Göfis","location":{"longitude":9.63135489394097,"latitude":47.235709},"population":3312}